setup.py
yamata/__init__.py
yamata.egg-info/PKG-INFO
yamata.egg-info/SOURCES.txt
yamata.egg-info/dependency_links.txt
yamata.egg-info/top_level.txt